purplship/__init__.py
purplship/api/__init__.py
purplship/api/gateway.py
purplship/api/interface.py
purplship/api/mapper.py
purplship/api/proxy.py
purplship/core/__init__.py
purplship/core/errors.py
purplship/core/metadata.py
purplship/core/models.py
purplship/core/settings.py
purplship/core/units.py
purplship/core/utils/__init__.py
purplship/core/utils/datetime.py
purplship/core/utils/dict.py
purplship/core/utils/enum.py
purplship/core/utils/helpers.py
purplship/core/utils/log.py
purplship/core/utils/number.py
purplship/core/utils/pipeline.py
purplship/core/utils/serializable.py
purplship/core/utils/soap.py
purplship/core/utils/string.py
purplship/core/utils/transformer.py
purplship/core/utils/xml.py
purplship/mappers/__init__.py
purplship/providers/__init__.py
purplship/references.py
purplship/universal/__init__.py
purplship/universal/mappers/__init__.py
purplship/universal/mappers/rating_proxy.py
purplship/universal/providers/__init__.py
purplship/universal/providers/rating/__init__.py
purplship/universal/providers/rating/rate.py
purplship/universal/providers/rating/utils.py
purplship-2022.2.dist-info/WHEEL
purplship-2022.2.dist-info/METADATA
purplship-2022.2.dist-info/RECORD
