Metadata-Version: 2.1
Name: purplship
Version: 2022.2
Summary: Multi-carrier shipping API integration with python
Home-page: https://next.purplship.com/docs/guides/sdk
License: Apache-2.0
Author: Purplship
Author-email: hello@purplship.com
Requires-Python: >=3.7,<4.0
Classifier: Intended Audience :: Developers
Classifier: License :: OSI Approved :: Apache Software License
Classifier: Operating System :: OS Independent
Classifier: Programming Language :: Python :: 3
Classifier: Programming Language :: Python :: 3.10
Classifier: Programming Language :: Python :: 3.7
Classifier: Programming Language :: Python :: 3.8
Classifier: Programming Language :: Python :: 3.9
Requires-Dist: Pillow
Requires-Dist: PyPDF2
Requires-Dist: jstruct
Requires-Dist: lxml
Requires-Dist: lxml-stubs
Requires-Dist: phonenumbers
Requires-Dist: py-soap
Requires-Dist: python-barcode
Requires-Dist: simple_zpl2
Requires-Dist: xmltodict
Project-URL: Repository, https://github.com/purplship/purplship
